candig_common-1.0.0-py2.7-nspkg.pth
candig/common/__init__.py
candig/common/_version.py
candig/common/cli.py
candig/common/run_tests.py
candig/common/utils.py
candig_common-1.0.0.dist-info/LICENSE
candig_common-1.0.0.dist-info/METADATA
candig_common-1.0.0.dist-info/WHEEL
candig_common-1.0.0.dist-info/entry_points.txt
candig_common-1.0.0.dist-info/namespace_packages.txt
candig_common-1.0.0.dist-info/top_level.txt
candig_common-1.0.0.dist-info/zip-safe
candig_common-1.0.0.dist-info/RECORD
