Metadata-Version: 2.1
Name: candig-common
Version: 1.0.0
Summary: Common utilities for CanDIG packages
Home-page: https://github.com/candig/candig-common
Author: CanDIG Team
Author-email: info@distributedgenomics.ca
License: Apache License 2.0
Keywords: genomics,reference
Platform: UNKNOWN
Classifier: Intended Audience :: Science/Research
Classifier: License :: OSI Approved :: Apache Software License
Classifier: Natural Language :: English
Classifier: Programming Language :: Python :: 3.6
Classifier: Programming Language :: Python :: 3.7
Classifier: Topic :: Scientific/Engineering :: Bio-Informatics
Requires-Dist: humanize
Requires-Dist: PyYAML
